{
  "bootstrap_iters": 10000,
  "bootstrap_seed": 20260223,
  "ci95_high": 0.29393883,
  "ci95_low": 0.28001992,
  "execution_reality_status": "PASS",
  "ingest_status": "PASS",
  "max_drawdown_proxy": 0,
  "mean_pnl_per_trade": 0.28702796,
  "message": "Expectancy PASS with positive lower CI, PSR threshold, and MinTRL satisfied.",
  "min_n_trades": 200,
  "min_trl": 2,
  "min_trl_trades": 3.6,
  "next_action": "npm run -s edge:profit:00:overfit",
  "profit_factor": 999,
  "psr0": 1,
  "psr_min": 0.95,
  "rationale": "CI lower > 0, PSR and MinTRL thresholds satisfied.",
  "reason_code": "NONE",
  "run_id": "b68b470a2f03",
  "schema_version": "1.0.0",
  "sharpe_proxy": 67.20483018,
  "status": "PASS",
  "stddev_pnl": 0.06779911,
  "trades_n": 360,
  "winrate": 1
}
